pypidb/__init__.py
pypidb/__main__.py
pypidb/_adapters.py
pypidb/_auth.py
pypidb/_cache.py
pypidb/_compat.py
pypidb/_db.py
pypidb/_exceptions.py
pypidb/_github.py
pypidb/_html.py
pypidb/_lp.py
pypidb/_pagure.py
pypidb/_patch.py
pypidb/_pypi.py
pypidb/_rtd.py
pypidb/_rules.py
pypidb/_scm_url_cleaner.py
pypidb/_similarity.py
pypidb/_stdlib.py
pypidb/_types.py
pypidb/_url_extract.py
pypidb/_version.py
pypidb/cli.py
pypidb/park_providers.txt
pypidb-0.2.4.dist-info/LICENSE
pypidb-0.2.4.dist-info/METADATA
pypidb-0.2.4.dist-info/WHEEL
pypidb-0.2.4.dist-info/entry_points.txt
pypidb-0.2.4.dist-info/top_level.txt
pypidb-0.2.4.dist-info/version.txt
pypidb-0.2.4.dist-info/RECORD
