Metadata-Version: 2.1
Name: pypidb
Version: 0.2.4
Summary: Local database of PyPI metadata to find VCS URLs
Home-page: https://github.com/jayvdb/pypidb
Author-email: jayvdb@gmail.com
License: Apache-2.0
Platform: UNKNOWN
Classifier: Environment :: Console
Classifier: Environment :: Web Environment
Classifier: Intended Audience :: Developers
Classifier: Intended Audience :: Science/Research
Classifier: Intended Audience :: System Administrators
Classifier: License :: OSI Approved :: Apache Software License
Classifier: Operating System :: OS Independent
Classifier: Programming Language :: Python :: 2.7
Classifier: Programming Language :: Python :: 3.5
Classifier: Programming Language :: Python :: 3.6
Classifier: Programming Language :: Python :: 3.7
Classifier: Programming Language :: Python :: 3.8
Classifier: Programming Language :: Python :: Implementation :: CPython
Classifier: Development Status :: 3 - Alpha
Requires-Python: >=2.7,!=3.0.*,!=3.1.*,!=3.2.*,!=3.3.*,!=3.4.*
Requires-Dist: CacheControl
Requires-Dist: appdirs
Requires-Dist: brotlipy
Requires-Dist: cachetools
Requires-Dist: click
Requires-Dist: diskcache
Requires-Dist: dns-cache
Requires-Dist: fake-useragent
Requires-Dist: https-everywhere
Requires-Dist: lockfile
Requires-Dist: logging-helper
Requires-Dist: lplight
Requires-Dist: lxml
Requires-Dist: requests[security]
Requires-Dist: socialregexes
Requires-Dist: stdlib-list
Requires-Dist: textdistance
Requires-Dist: unidiff
Requires-Dist: urlextract
